{"team": "TEN", "games": [{"home_team": "PHI", "away_team": "TEN", "game_id": 2019080861, "week": 1, "season": 2019, "state_of_game": "POST", "game_url": "http://www.nfl.com/liveupdate/game-center/2019080861/2019080861_gtd.json", "home_score": 10, "away_score": 27, "date": "08-08-2019", "type": "pre_season"}, {"home_team": "TEN", "away_team": "NE", "game_id": 2019081755, "week": 2, "season": 2019, "state_of_game": "POST", "game_url": "http://www.nfl.com/liveupdate/game-center/2019081755/2019081755_gtd.json", "home_score": 17, "away_score": 22, "date": "08-17-2019", "type": "pre_season"}, {"home_team": "TEN", "away_team": "PIT", "game_id": 2019082551, "week": 3, "season": 2019, "state_of_game": "POST", "game_url": "http://www.nfl.com/liveupdate/game-center/2019082551/2019082551_gtd.json", "home_score": 6, "away_score": 18, "date": "08-25-2019", "type": "pre_season"}, {"home_team": "CHI", "away_team": "TEN", "game_id": 2019082953, "week": 4, "season": 2019, "state_of_game": "POST", "game_url": "http://www.nfl.com/liveupdate/game-center/2019082953/2019082953_gtd.json", "home_score": 15, "away_score": 19, "date": "08-29-2019", "type": "pre_season"}, {"home_team": "CLE", "away_team": "TEN", "game_id": 2019090801, "week": 1, "season": 2019, "state_of_game": "POST", "game_url": "http://www.nfl.com/liveupdate/game-center/2019090801/2019090801_gtd.json", "home_score": 13, "away_score": 43, "date": "09-08-2019", "type": "regular"}, {"home_team": "TEN", "away_team": "IND", "game_id": 2019091508, "week": 2, "season": 2019, "state_of_game": "POST", "game_url": "http://www.nfl.com/liveupdate/game-center/2019091508/2019091508_gtd.json", "home_score": 17, "away_score": 19, "date": "09-15-2019", "type": "regular"}, {"home_team": "JAX", "away_team": "TEN", "game_id": 2019091900, "week": 3, "season": 2019, "state_of_game": "POST", "game_url": "http://www.nfl.com/liveupdate/game-center/2019091900/2019091900_gtd.json", "home_score": 20, "away_score": 7, "date": "09-19-2019", "type": "regular"}, {"home_team": "ATL", "away_team": "TEN", "game_id": 2019092900, "week": 4, "season": 2019, "state_of_game": "POST", "game_url": "http://www.nfl.com/liveupdate/game-center/2019092900/2019092900_gtd.json", "home_score": 10, "away_score": 24, "date": "09-29-2019", "type": "regular"}, {"home_team": "TEN", "away_team": "BUF", "game_id": 2019100608, "week": 5, "season": 2019, "state_of_game": "POST", "game_url": "http://www.nfl.com/liveupdate/game-center/2019100608/2019100608_gtd.json", "home_score": 7, "away_score": 14, "date": "10-06-2019", "type": "regular"}, {"home_team": "DEN", "away_team": "TEN", "game_id": 2019101309, "week": 6, "season": 2019, "state_of_game": "POST", "game_url": "http://www.nfl.com/liveupdate/game-center/2019101309/2019101309_gtd.json", "home_score": 16, "away_score": 0, "date": "10-13-2019", "type": "regular"}, {"home_team": "TEN", "away_team": "LAC", "game_id": 2019102008, "week": 7, "season": 2019, "state_of_game": "POST", "game_url": "http://www.nfl.com/liveupdate/game-center/2019102008/2019102008_gtd.json", "home_score": 23, "away_score": 20, "date": "10-20-2019", "type": "regular"}, {"home_team": "TEN", "away_team": "TB", "game_id": 2019102708, "week": 8, "season": 2019, "state_of_game": "POST", "game_url": "http://www.nfl.com/liveupdate/game-center/2019102708/2019102708_gtd.json", "home_score": 27, "away_score": 23, "date": "10-27-2019", "type": "regular"}, {"home_team": "CAR", "away_team": "TEN", "game_id": 2019110302, "week": 9, "season": 2019, "state_of_game": "POST", "game_url": "http://www.nfl.com/liveupdate/game-center/2019110302/2019110302_gtd.json", "home_score": 30, "away_score": 20, "date": "11-03-2019", "type": "regular"}, {"home_team": "TEN", "away_team": "KC", "game_id": 2019111007, "week": 10, "season": 2019, "state_of_game": "POST", "game_url": "http://www.nfl.com/liveupdate/game-center/2019111007/2019111007_gtd.json", "home_score": 35, "away_score": 32, "date": "11-10-2019", "type": "regular"}, {"home_team": "TEN", "away_team": "JAX", "game_id": 2019112408, "week": 12, "season": 2019, "state_of_game": "POST", "game_url": "http://www.nfl.com/liveupdate/game-center/2019112408/2019112408_gtd.json", "home_score": 42, "away_score": 20, "date": "11-24-2019", "type": "regular"}, {"home_team": "IND", "away_team": "TEN", "game_id": 2019120103, "week": 13, "season": 2019, "state_of_game": "POST", "game_url": "http://www.nfl.com/liveupdate/game-center/2019120103/2019120103_gtd.json", "home_score": 17, "away_score": 31, "date": "12-01-2019", "type": "regular"}, {"home_team": "OAK", "away_team": "TEN", "game_id": 2019120812, "week": 14, "season": 2019, "state_of_game": "POST", "game_url": "http://www.nfl.com/liveupdate/game-center/2019120812/2019120812_gtd.json", "home_score": 21, "away_score": 42, "date": "12-08-2019", "type": "regular"}, {"home_team": "TEN", "away_team": "HOU", "game_id": 2019121507, "week": 15, "season": 2019, "state_of_game": "POST", "game_url": "http://www.nfl.com/liveupdate/game-center/2019121507/2019121507_gtd.json", "home_score": 21, "away_score": 24, "date": "12-15-2019", "type": "regular"}, {"home_team": "TEN", "away_team": "NO", "game_id": 2019122210, "week": 16, "season": 2019, "state_of_game": "POST", "game_url": "http://www.nfl.com/liveupdate/game-center/2019122210/2019122210_gtd.json", "home_score": 28, "away_score": 38, "date": "12-22-2019", "type": "regular"}, {"home_team": "HOU", "away_team": "TEN", "game_id": 2019122906, "week": 17, "season": 2019, "state_of_game": "POST", "game_url": "http://www.nfl.com/liveupdate/game-center/2019122906/2019122906_gtd.json", "home_score": 14, "away_score": 35, "date": "12-29-2019", "type": "regular"}, {"home_team": "NE", "away_team": "TEN", "game_id": 2020010401, "week": 18, "season": 2019, "state_of_game": "POST", "game_url": "http://www.nfl.com/liveupdate/game-center/2020010401/2020010401_gtd.json", "home_score": 13.0, "away_score": 20.0, "date": "01-04-2020", "type": "post_season"}, {"home_team": "BAL", "away_team": "TEN", "game_id": 2020011101, "week": 18, "season": 2019, "state_of_game": "POST", "game_url": "http://www.nfl.com/liveupdate/game-center/2020011101/2020011101_gtd.json", "home_score": 12.0, "away_score": 28.0, "date": "01-11-2020", "type": "post_season"}, {"home_team": "KC", "away_team": "TEN", "game_id": 2020011900, "week": 18, "season": 2019, "state_of_game": "POST", "game_url": "http://www.nfl.com/liveupdate/game-center/2020011900/2020011900_gtd.json", "home_score": 35.0, "away_score": 24.0, "date": "01-19-2020", "type": "post_season"}], "bye_week": 11}