{"team": "CIN", "games": [{"home_team": "NE", "away_team": "WAS", "game_id": 2018080958, "week": 1, "season": 2018, "state_of_game": "POST", "game_url": "http://www.nfl.com/liveupdate/game-center/2018080958/2018080958_gtd.json", "home_score": 26, "away_score": 17, "date": "08-09-2018"}, {"home_team": "WAS", "away_team": "NYJ", "game_id": 2018081651, "week": 2, "season": 2018, "state_of_game": "POST", "game_url": "http://www.nfl.com/liveupdate/game-center/2018081651/2018081651_gtd.json", "home_score": 15, "away_score": 13, "date": "08-16-2018"}, {"home_team": "WAS", "away_team": "DEN", "game_id": 2018082455, "week": 3, "season": 2018, "state_of_game": "POST", "game_url": "http://www.nfl.com/liveupdate/game-center/2018082455/2018082455_gtd.json", "home_score": 17, "away_score": 29, "date": "08-24-2018"}, {"home_team": "BAL", "away_team": "WAS", "game_id": 2018083053, "week": 4, "season": 2018, "state_of_game": "POST", "game_url": "http://www.nfl.com/liveupdate/game-center/2018083053/2018083053_gtd.json", "home_score": 30, "away_score": 20, "date": "08-30-2018"}], "bye_week": 5}